{
    "account": "Konto",
    "done": "Getan",
    "ask your caretaker": "Bitten Sie Ihren Hausmeister, diesen Code einzugeben",
    "successfully paired": "Erfolgreich gekoppelt",
    "its time for": "Es ist Zeit für",
    "no medicine": "keine Medizin",
    "next doses are": "Die nächsten Dosen sind",
    "take it now": "Nimm es jetzt",
    "snooze": "Schlummern",
    "press and hold": "Gedrückt halten, um als vergeben zu markieren",
    "marked as taken": "Als genommen markiert",
    "medication list": "Medikamentenliste",
    "3 days log": "3 Tage Protokoll",
    "no record":"keine Aufzeichnungen",
    "settings": "Die Einstellungen",
    "medications": "Medikamente",
    "taken at": "Genommen bei",
    "skipped": "Übersprungen",
    "notifications": "Benachrichtigungen",
    "snooze duration": "Schlummerdauer",
    "snooze time": "Schlummerzeit",
    "languages": "Sprachen",
    "log out": "Ausloggen",
    "five minutes": "Fünf Minuten",
    "ten minutes": "Zehn Minuten",
    "fifteen minutes": "Fünfzehn Minuten"
}